setup.py
fabix/__init__.py
fabix/mongodb.py
fabix/nginx.py
fabix/project.py
fabix/python.py
fabix.egg-info/PKG-INFO
fabix.egg-info/SOURCES.txt
fabix.egg-info/dependency_links.txt
fabix.egg-info/requires.txt
fabix.egg-info/top_level.txt
fabix/aws/__init__.py
fabix/aws/ec2.py
fabix/aws/s3.py
fabix/system/__init__.py
fabix/system/crontab.py
fabix/system/upstart.py