Metadata-Version: 1.1
Name: fabix
Version: 0.0.3
Summary: Fabix is a serie of functions built on top of fabric and cuisine to easily deploy python web projects.
Home-page: http://github.com/quatix/fabix
Author: Rodrigo Machado
Author-email: rcmachado@gmail.com
License: MIT
Keywords: fabric,cuisine,fabix
Platform: UNKNOWN
Classifier: Development Status :: 3 - Alpha
Classifier: Environment :: Console
Classifier: Intended Audience :: Developers
Classifier: Intended Audience :: System Administrators
Classifier: License :: OSI Approved :: MIT License
Classifier: Natural Language :: English
Classifier: Operating System :: POSIX :: Linux
Classifier: Programming Language :: Python :: 2.7
Classifier: Topic :: Software Development
Classifier: Topic :: Software Development :: Build Tools
Classifier: Topic :: Software Development :: Libraries :: Python Modules
Classifier: Topic :: System :: Systems Administration
